[
  {
    "persona": "Persona: Omar El-Sayed\n\nBackground:\nOmar has always been drawn to construction and development. After years of working in engineering, he moved into property development, focusing on large-scale residential projects in Cairo.\n\nDemographics:\nAge: 46\nGender: Male\nEducation: Bachelor's in Civil Engineering\nProfession: Head of Property Development\nIncome: EGP 450,000\n\nFinancial Situation:\nOmar prefers steady growth in his investments and keeps a diverse portfolio. He manages his finances with a long-term perspective, ensuring security for his family's future.\n\nBrowsing Habits:\nOmar values quick access to relevant information and dislikes websites that require multiple logins or excessive navigation. He prefers straightforward, functional interfaces.\n\nProfessional Life:\nOmar leads a team of developers, architects, and engineers, overseeing projects from inception to completion. His role is demanding, balancing strategic oversight with operational details.\n\nPersonal Style:\nOmar is organized, thoughtful, and values reliability. He prioritizes clear communication and appreciates technology that simplifies complex processes.\n\nPrimary Goal: To implement a system that boosts call management capabilities and integrates with project timelines.\nPain Points: Slow response times; Limited support for Arabic language; Complex setup processes",
    "intent": "To implement a system that boosts call management capabilities and integrates with project timelines.",
    "name": "Omar El-Sayed",
    "age": 46,
    "gender": "Male",
    "country": "Egypt",
    "occupation": "Head of Property Development",
    "education": "Bachelor's in Civil Engineering",
    "incomeLevel": "high",
    "income": "EGP 450,000",
    "techSavviness": "intermediate",
    "primaryGoal": "To implement a system that boosts call management capabilities and integrates with project timelines.",
    "painPoints": [
      "Slow response times",
      "Limited support for Arabic language",
      "Complex setup processes"
    ],
    "background": "Omar has always been drawn to construction and development. After years of working in engineering, he moved into property development, focusing on large-scale residential projects in Cairo.",
    "financialSituation": "Omar prefers steady growth in his investments and keeps a diverse portfolio. He manages his finances with a long-term perspective, ensuring security for his family's future.",
    "browsingHabits": "Omar values quick access to relevant information and dislikes websites that require multiple logins or excessive navigation. He prefers straightforward, functional interfaces.",
    "professionalLife": "Omar leads a team of developers, architects, and engineers, overseeing projects from inception to completion. His role is demanding, balancing strategic oversight with operational details.",
    "personalStyle": "Omar is organized, thoughtful, and values reliability. He prioritizes clear communication and appreciates technology that simplifies complex processes.",
    "context": "Omar's work involves constant communication with diverse stakeholders, including international partners. He seeks tools that facilitate seamless interaction across different languages and time zones, improving efficiency and collaboration.",
    "relevanceScore": 10
  },
  {
    "persona": "Persona: Laura Martinez\n\nBackground:\nLaura grew up in Seville, Spain, and has always been passionate about real estate. She climbed the ranks from a sales assistant to becoming a leasing manager. She loves helping people find their perfect homes and is driven by her desire to streamline processes and improve customer experiences.\n\nDemographics:\nAge: 42\nGender: Female\nEducation: Bachelor's in Business Administration\nProfession: Leasing Manager\nIncome: €85,000\n\nFinancial Situation:\nLaura is financially savvy, regularly investing in stocks and ensuring she saves 20% of her income annually. She enjoys luxury vacations but always plans them within her budget.\n\nBrowsing Habits:\nLaura prefers websites that offer quick solutions and efficient interfaces. She dislikes cluttered websites and values a streamlined, user-friendly design.\n\nProfessional Life:\nLaura manages a team of six and oversees the leasing operations of several properties. Her day is filled with client meetings and strategic planning, requiring her to manage her time meticulously.\n\nPersonal Style:\nLaura is organized, decisive, and appreciates clear communication. She often relies on her smartphone for tasks and prefers texting over calls.\n\nPrimary Goal: To find a tool that efficiently manages and tracks all client interactions.\nPain Points: Long wait times for customer service; Complicated navigation; Lack of integration with existing tools",
    "intent": "To find a tool that efficiently manages and tracks all client interactions.",
    "name": "Laura Martinez",
    "age": 42,
    "gender": "Female",
    "country": "Spain",
    "occupation": "Leasing Manager",
    "education": "Bachelor's in Business Administration",
    "incomeLevel": "high",
    "income": "€85,000",
    "techSavviness": "intermediate",
    "primaryGoal": "To find a tool that efficiently manages and tracks all client interactions.",
    "painPoints": [
      "Long wait times for customer service",
      "Complicated navigation",
      "Lack of integration with existing tools"
    ],
    "background": "Laura grew up in Seville, Spain, and has always been passionate about real estate. She climbed the ranks from a sales assistant to becoming a leasing manager. She loves helping people find their perfect homes and is driven by her desire to streamline processes and improve customer experiences.",
    "financialSituation": "Laura is financially savvy, regularly investing in stocks and ensuring she saves 20% of her income annually. She enjoys luxury vacations but always plans them within her budget.",
    "browsingHabits": "Laura prefers websites that offer quick solutions and efficient interfaces. She dislikes cluttered websites and values a streamlined, user-friendly design.",
    "professionalLife": "Laura manages a team of six and oversees the leasing operations of several properties. Her day is filled with client meetings and strategic planning, requiring her to manage her time meticulously.",
    "personalStyle": "Laura is organized, decisive, and appreciates clear communication. She often relies on her smartphone for tasks and prefers texting over calls.",
    "context": "Laura works in a competitive industry where time is money. She's often multitasking and requires quick access to information, particularly during client meetings. Her decision-making is data-driven, and she values technology that supports her efficiency.",
    "relevanceScore": 9
  },
  {
    "persona": "Persona: Anya Patel\n\nBackground:\nGrowing up in Mumbai, Anya was inspired by the city's dynamic real estate landscape. Her MBA propelled her into a successful career managing commercial leases for large corporations.\n\nDemographics:\nAge: 34\nGender: Female\nEducation: MBA in Real Estate Management\nProfession: Commercial Lease Manager\nIncome: ₹12,00,000\n\nFinancial Situation:\nAnya is financially disciplined, with diversified investments in real estate and mutual funds. She prefers to automate her savings and is conscious about spending.\n\nBrowsing Habits:\nAnya is a power user who enjoys exploring new technologies. She prefers platforms that offer customization and robust analytics, often switching between devices seamlessly.\n\nProfessional Life:\nAnya's role involves negotiating leases, optimizing space utilization, and liaising with corporate clients. Her work is fast-paced, requiring strategic planning and quick decision-making.\n\nPersonal Style:\nAnya is assertive, analytical, and thrives in high-pressure environments. She values direct communication and leverages technology to maintain productivity.\n\nPrimary Goal: To find an AI-driven tool that enhances call handling and provides insightful analytics.\nPain Points: Lag in data updates; Lack of training resources; Incompatibility with existing systems",
    "intent": "To find an AI-driven tool that enhances call handling and provides insightful analytics.",
    "name": "Anya Patel",
    "age": 34,
    "gender": "Female",
    "country": "India",
    "occupation": "Commercial Lease Manager",
    "education": "MBA in Real Estate Management",
    "incomeLevel": "high",
    "income": "₹12,00,000",
    "techSavviness": "advanced",
    "primaryGoal": "To find an AI-driven tool that enhances call handling and provides insightful analytics.",
    "painPoints": [
      "Lag in data updates",
      "Lack of training resources",
      "Incompatibility with existing systems"
    ],
    "background": "Growing up in Mumbai, Anya was inspired by the city's dynamic real estate landscape. Her MBA propelled her into a successful career managing commercial leases for large corporations.",
    "financialSituation": "Anya is financially disciplined, with diversified investments in real estate and mutual funds. She prefers to automate her savings and is conscious about spending.",
    "browsingHabits": "Anya is a power user who enjoys exploring new technologies. She prefers platforms that offer customization and robust analytics, often switching between devices seamlessly.",
    "professionalLife": "Anya's role involves negotiating leases, optimizing space utilization, and liaising with corporate clients. Her work is fast-paced, requiring strategic planning and quick decision-making.",
    "personalStyle": "Anya is assertive, analytical, and thrives in high-pressure environments. She values direct communication and leverages technology to maintain productivity.",
    "context": "Anya's work demands a blend of strategic foresight and operational efficiency. She seeks platforms that not only facilitate communication but also offer predictive insights to drive business growth. Her decision-making is supported by data analytics and market trends.",
    "relevanceScore": 9
  },
  {
    "persona": "Persona: Emily Cheng\n\nBackground:\nEmily grew up in a small town in Ohio and moved to New York City to pursue her career in real estate. Her passion lies in helping people find comfortable homes, and she is eager to learn and grow within the industry.\n\nDemographics:\nAge: 29\nGender: Female\nEducation: Associate's Degree in Real Estate Management\nProfession: Property Management Assistant\nIncome: $55,000\n\nFinancial Situation:\nEmily is still learning to manage her finances, often using budgeting apps to track spending. She saves occasionally but is focused on paying off student loans.\n\nBrowsing Habits:\nEmily prefers mobile browsing due to her on-the-go lifestyle. She appreciates clear, easy-to-navigate websites but often struggles with complex forms and settings.\n\nProfessional Life:\nEmily supports the property management team with administrative tasks and client interactions. She juggles multiple responsibilities and learns through hands-on experience.\n\nPersonal Style:\nEmily is enthusiastic, team-oriented, and values clear instructions. She is still building confidence with technology and appreciates user-friendly interfaces that offer tutorials.\n\nPrimary Goal: To find a straightforward system that aids in managing client calls efficiently.\nPain Points: Difficult interface; Lack of mobile optimization; Overwhelming amount of options",
    "intent": "To find a straightforward system that aids in managing client calls efficiently.",
    "name": "Emily Cheng",
    "age": 29,
    "gender": "Female",
    "country": "United States",
    "occupation": "Property Management Assistant",
    "education": "Associate's Degree in Real Estate Management",
    "incomeLevel": "medium",
    "income": "$55,000",
    "techSavviness": "beginner",
    "primaryGoal": "To find a straightforward system that aids in managing client calls efficiently.",
    "painPoints": [
      "Difficult interface",
      "Lack of mobile optimization",
      "Overwhelming amount of options"
    ],
    "background": "Emily grew up in a small town in Ohio and moved to New York City to pursue her career in real estate. Her passion lies in helping people find comfortable homes, and she is eager to learn and grow within the industry.",
    "financialSituation": "Emily is still learning to manage her finances, often using budgeting apps to track spending. She saves occasionally but is focused on paying off student loans.",
    "browsingHabits": "Emily prefers mobile browsing due to her on-the-go lifestyle. She appreciates clear, easy-to-navigate websites but often struggles with complex forms and settings.",
    "professionalLife": "Emily supports the property management team with administrative tasks and client interactions. She juggles multiple responsibilities and learns through hands-on experience.",
    "personalStyle": "Emily is enthusiastic, team-oriented, and values clear instructions. She is still building confidence with technology and appreciates user-friendly interfaces that offer tutorials.",
    "context": "Emily's role requires her to assist in several areas, and her time is often fragmented. She needs tools that simplify her tasks and provide clear instructions, as she often handles calls on the go, especially during commutes.",
    "relevanceScore": 7
  },
  {
    "persona": "Persona: Fatima Ali\n\nBackground:\nFatima grew up in Dubai and pursued her passion for real estate by studying finance. She is driven by a desire to innovate and improve real estate investment strategies.\n\nDemographics:\nAge: 28\nGender: Female\nEducation: Master's in Real Estate Finance\nProfession: Real Estate Development Analyst\nIncome: AED 300,000\n\nFinancial Situation:\nFatima is financially secure, with investments in both local and international real estate markets. She is meticulous in her financial planning and prioritizes long-term stability.\n\nBrowsing Habits:\nHighly tech-savvy, Fatima enjoys exploring new technologies and prefers websites that offer innovative features and in-depth analytics. She values efficiency and robust data tools.\n\nProfessional Life:\nFatima analyzes real estate trends and investment opportunities, supporting strategic decisions within her company. Her role is data-driven and requires continuous learning and adaptation.\n\nPersonal Style:\nFatima is analytical, goal-oriented, and thrives on challenges. She values direct communication and appreciates platforms that provide comprehensive insights and automation.\n\nPrimary Goal: To utilize a data-driven platform that streamlines call management and supports strategic analyses.\nPain Points: Lack of advanced analytical tools; Inconsistent user experience; Limited integration with analytics software",
    "intent": "To utilize a data-driven platform that streamlines call management and supports strategic analyses.",
    "name": "Fatima Ali",
    "age": 28,
    "gender": "Female",
    "country": "United Arab Emirates",
    "occupation": "Real Estate Development Analyst",
    "education": "Master's in Real Estate Finance",
    "incomeLevel": "high",
    "income": "AED 300,000",
    "techSavviness": "advanced",
    "primaryGoal": "To utilize a data-driven platform that streamlines call management and supports strategic analyses.",
    "painPoints": [
      "Lack of advanced analytical tools",
      "Inconsistent user experience",
      "Limited integration with analytics software"
    ],
    "background": "Fatima grew up in Dubai and pursued her passion for real estate by studying finance. She is driven by a desire to innovate and improve real estate investment strategies.",
    "financialSituation": "Fatima is financially secure, with investments in both local and international real estate markets. She is meticulous in her financial planning and prioritizes long-term stability.",
    "browsingHabits": "Highly tech-savvy, Fatima enjoys exploring new technologies and prefers websites that offer innovative features and in-depth analytics. She values efficiency and robust data tools.",
    "professionalLife": "Fatima analyzes real estate trends and investment opportunities, supporting strategic decisions within her company. Her role is data-driven and requires continuous learning and adaptation.",
    "personalStyle": "Fatima is analytical, goal-oriented, and thrives on challenges. She values direct communication and appreciates platforms that provide comprehensive insights and automation.",
    "context": "Fatima's work requires a deep understanding of market dynamics and client needs. She values platforms that offer predictive insights and data-driven decision-making, supporting her role in shaping strategic investments.",
    "relevanceScore": 9
  }
]